tzc/__init__.py
tzc/main.py
tzc-1.0.6.dist-info/LICENSE
tzc-1.0.6.dist-info/METADATA
tzc-1.0.6.dist-info/WHEEL
tzc-1.0.6.dist-info/entry_points.txt
tzc-1.0.6.dist-info/top_level.txt
tzc-1.0.6.dist-info/RECORD
