Metadata-Version: 2.1
Name: tzc
Version: 1.0.6
Summary: copies input to output, converting timezone in any lines beginning with an ISO-8601 timestamp
Home-page: https://github.com/rstms/tzc
Author: Matt Krueger
License: MIT License
Project-URL: Issues, https://github.com/rstms/tzc/issues
Project-URL: CI, https://github.com/rstms/tzc/actions
Project-URL: Changelog, https://github.com/rstms/tzc/releases
Platform: UNKNOWN
Requires-Python: >=3.6
Requires-Dist: click
Requires-Dist: arrow
Provides-Extra: test
Requires-Dist: pytest ; extra == 'test'
Requires-Dist: pytest-datadir ; extra == 'test'
